Metadata-Version: 2.1
Name: amelpersik-custom-serializer
Version: 0.2.3
Summary: Python JSON and XML serializer
Home-page: UNKNOWN
Author: amelpersik
Author-email: st.dasha.st@gmail.com
License: MIT
Platform: UNKNOWN
